faraday_agent_dispatcher/__init__.py
faraday_agent_dispatcher/config.py
faraday_agent_dispatcher/dispatcher.py
faraday_agent_dispatcher/dispatcher_io.py
faraday_agent_dispatcher/example_config.ini
faraday_agent_dispatcher/example_config.yaml
faraday_agent_dispatcher/executor.py
faraday_agent_dispatcher/executor_helper.py
faraday_agent_dispatcher/logger.py
faraday_agent_dispatcher/cli/__init__.py
faraday_agent_dispatcher/cli/main.py
faraday_agent_dispatcher/cli/wizard.py
faraday_agent_dispatcher/cli/utils/__init__.py
faraday_agent_dispatcher/cli/utils/exceptions.py
faraday_agent_dispatcher/cli/utils/general_inputs.py
faraday_agent_dispatcher/cli/utils/general_prompts.py
faraday_agent_dispatcher/cli/utils/model_load.py
faraday_agent_dispatcher/static/executors/official/appscan.py
faraday_agent_dispatcher/static/executors/official/arachni.py
faraday_agent_dispatcher/static/executors/official/burp.py
faraday_agent_dispatcher/static/executors/official/cisco_cybervision.py
faraday_agent_dispatcher/static/executors/official/codeql.py
faraday_agent_dispatcher/static/executors/official/crackmapexec.py
faraday_agent_dispatcher/static/executors/official/dependabot.py
faraday_agent_dispatcher/static/executors/official/github_secrets.py
faraday_agent_dispatcher/static/executors/official/gvm_openvas.py
faraday_agent_dispatcher/static/executors/official/insightvm.py
faraday_agent_dispatcher/static/executors/official/microsoft_defender.py
faraday_agent_dispatcher/static/executors/official/nessus.py
faraday_agent_dispatcher/static/executors/official/nikto2.py
faraday_agent_dispatcher/static/executors/official/nmap.py
faraday_agent_dispatcher/static/executors/official/nuclei.py
faraday_agent_dispatcher/static/executors/official/openvas_legacy.py
faraday_agent_dispatcher/static/executors/official/qualys.py
faraday_agent_dispatcher/static/executors/official/report_processor.py
faraday_agent_dispatcher/static/executors/official/shodan2.py
faraday_agent_dispatcher-3.9.1.dist-info/licenses/AUTHORS.rst
faraday_agent_dispatcher-3.9.1.dist-info/licenses/COPYING
faraday_agent_dispatcher-3.9.1.dist-info/METADATA
faraday_agent_dispatcher-3.9.1.dist-info/WHEEL
faraday_agent_dispatcher-3.9.1.dist-info/entry_points.txt
faraday_agent_dispatcher-3.9.1.dist-info/top_level.txt
faraday_agent_dispatcher-3.9.1.dist-info/RECORD
