Metadata-Version: 2.4
Name: faraday_agent_dispatcher
Version: 3.9.1
Summary: Faraday agent dispatcher to communicate an agent to faraday
Home-page: https://github.com/infobyte/faraday_agent_dispatcher
Author: Faraday Development Team
Author-email: devel@faradaysec.com
License: GNU General Public License v3
Keywords: faraday integration
Classifier: Development Status :: 5 - Production/Stable
Classifier: Intended Audience :: Developers
Classifier: License :: OSI Approved :: GNU General Public License v3 (GPLv3)
Classifier: Natural Language :: English
Classifier: Programming Language :: Python :: 3
Classifier: Programming Language :: Python :: 3.8
Classifier: Programming Language :: Python :: 3.9
Classifier: Programming Language :: Python :: 3.10
Requires-Python: >=3.8
License-File: COPYING
License-File: AUTHORS.rst
Requires-Dist: Click>=7
Requires-Dist: websockets
Requires-Dist: aiohttp
Requires-Dist: syslog_rfc5424_formatter
Requires-Dist: requests
Requires-Dist: itsdangerous
Requires-Dist: faraday-plugins>=1.26.0
Requires-Dist: python-owasp-zap-v2.4
Requires-Dist: python-gvm
Requires-Dist: faraday_agent_parameters_types>=1.9.0
Requires-Dist: pyyaml
Requires-Dist: psutil
Requires-Dist: pytenable
Requires-Dist: python-socketio==5.8.0
Requires-Dist: requests-ratelimiter
Provides-Extra: dev
Requires-Dist: giteasychangelog; extra == "dev"
Requires-Dist: flake8; extra == "dev"
Requires-Dist: pre-commit; extra == "dev"
Requires-Dist: black; extra == "dev"
Provides-Extra: test
Requires-Dist: pytest; extra == "test"
Requires-Dist: pytest-cov; extra == "test"
Requires-Dist: pytest-asyncio==0.18.3; extra == "test"
Provides-Extra: docs
Requires-Dist: mkdocs; extra == "docs"
Requires-Dist: mkdocs-material; extra == "docs"
Dynamic: author
Dynamic: author-email
Dynamic: classifier
Dynamic: description
Dynamic: description-content-type
Dynamic: home-page
Dynamic: keywords
Dynamic: license
Dynamic: license-file
Dynamic: provides-extra
Dynamic: requires-dist
Dynamic: requires-python
Dynamic: summary
